README.md
setup.py
src/vdk/plugin/logging_format/logging_format.py
src/vdk_logging_format.egg-info/PKG-INFO
src/vdk_logging_format.egg-info/SOURCES.txt
src/vdk_logging_format.egg-info/dependency_links.txt
src/vdk_logging_format.egg-info/entry_points.txt
src/vdk_logging_format.egg-info/requires.txt
src/vdk_logging_format.egg-info/top_level.txt
tests/test_logging_json.py